pymailgen/__init__.py
pymailgen/pymailgen.py
pymailgen/version.py
pymailgen-0.1.0.dist-info/METADATA
pymailgen-0.1.0.dist-info/WHEEL
pymailgen-0.1.0.dist-info/entry_points.txt
pymailgen-0.1.0.dist-info/top_level.txt
pymailgen-0.1.0.dist-info/RECORD
