Metadata-Version: 2.1
Name: pymailgen
Version: 0.1.0
Summary: Email generator from CSV metadata and text template
Home-page: https://github.com/toolleeo/pymailgen
Author: Tullio Facchinetti
Author-email: toolleeo@gmail.com
License: GPL-3
Platform: UNKNOWN
Classifier: Programming Language :: Python :: 3
Classifier: Operating System :: OS Independent
